logmux.py
logmux-0.1.1.dist-info/LICENSE
logmux-0.1.1.dist-info/METADATA
logmux-0.1.1.dist-info/WHEEL
logmux-0.1.1.dist-info/entry_points.txt
logmux-0.1.1.dist-info/top_level.txt
logmux-0.1.1.dist-info/RECORD
