Metadata-Version: 2.1
Name: logmux
Version: 0.1.1
Summary: Tail multiple log files, label their lines and combine them into one stream
Home-page: https://github.com/monacoremo/logmux
Author: monacoremo
Author-email: monacohacks@gmail.com
License: UNKNOWN
Keywords: logs tail monitoring
Platform: UNKNOWN
Classifier: Development Status :: 4 - Beta
Classifier: Intended Audience :: Developers
Classifier: Topic :: Software Development :: Build Tools
Classifier: Topic :: System :: Logging
Classifier: Topic :: System :: Monitoring
Classifier: License :: OSI Approved :: MIT License
Classifier: Programming Language :: Python :: 3.8
Classifier: Programming Language :: Python :: 3.7
Requires-Python: >=3.7, <4
Requires-Dist: click
Provides-Extra: test
Requires-Dist: pytest ; extra == 'test'
